LICENSE
README.md
setup.py
shady_tr/__init__.py
shady_tr/mapping.py
shady_tr/shady_text_randomizer.py
shady_tr.egg-info/PKG-INFO
shady_tr.egg-info/SOURCES.txt
shady_tr.egg-info/dependency_links.txt
shady_tr.egg-info/top_level.txt
tests/__init__.py
tests/data.py
tests/test_shady_tr.py