Metadata-Version: 2.1
Name: shady-tr
Version: 0.0.1
Summary: Helps to avoid spam-filters by replacing some characters in text with similar characters from other languages
Home-page: https://github.com/Ka3u6y6a/shady_text_randomizer
Author: Ka3u6y6a
Author-email: 
License: MIT License
Keywords: text randomizer random
Platform: UNKNOWN
Classifier: Programming Language :: Python :: 3
Classifier: License :: OSI Approved :: MIT License
Classifier: Operating System :: OS Independent
Requires-Python: >=3.6
License-File: LICENSE
